adcc/__init__.py
adcc-0.1.0.dist-info/METADATA
adcc-0.1.0.dist-info/WHEEL
adcc-0.1.0.dist-info/top_level.txt
adcc-0.1.0.dist-info/RECORD
