Metadata-Version: 2.1
Name: adcc
Version: 0.1.0
Summary: adcc:  Seamlessly connect your host program to ADC
Home-page: https://adc-connect.org
Author: Michael F. Herbst, Maximilian Scheurer
Author-email: adcc+developers@michael-herbst.com
License: LGPL v3
Platform: Linux
Platform: Mac OS-X
Classifier: Development Status :: 1 - Planning
Classifier: License :: OSI Approved :: GNU Lesser General Public License v3 (LGPLv3)
Classifier: License :: Free For Educational Use
Classifier: Intended Audience :: Science/Research
Classifier: Topic :: Scientific/Engineering :: Chemistry
Classifier: Topic :: Education
Classifier: Programming Language :: Python :: 3.5
Classifier: Programming Language :: Python :: 3.6
Classifier: Programming Language :: Python :: 3.7
Classifier: Operating System :: MacOS :: MacOS X
Classifier: Operating System :: POSIX :: Linux
Requires-Python: >=3.5
